piperbook/__init__.py
piperbook-2023.9.24.dist-info/entry_points.txt
piperbook-2023.9.24.dist-info/LICENSE
piperbook-2023.9.24.dist-info/WHEEL
piperbook-2023.9.24.dist-info/METADATA
piperbook-2023.9.24.dist-info/RECORD
