Metadata-Version: 2.1
Name: piperbook
Version: 2023.9.24
Summary: Uses piper-tts to convert epub files to audiobooks
Author-email: "Spencer T Royce, Esq." <str.esq@protonmail.com>
Requires-Python: >=3.11
Classifier: License :: OSI Approved :: MIT License
Classifier: Natural Language :: English
Classifier: Operating System :: POSIX :: Linux
Classifier: Programming Language :: Python
Classifier: Programming Language :: Python :: 3.11
Requires-Dist: beautifulsoup4==4.12.2
Requires-Dist: EbookLib==0.18
Requires-Dist: loguru==0.7.2
Requires-Dist: lxml==4.9.3
Requires-Dist: mutagen==1.47.0
Requires-Dist: piper-tts==1.2.0
Requires-Dist: typed-argparse==0.3.0
Requires-Dist: appdirs==1.4.4
Requires-Dist: pylint ~=2.14.0 ; extra == "dev"
Requires-Dist: toml ~=0.10.2 ; extra == "dev"
Requires-Dist: yapf ~=0.32.0 ; extra == "dev"
Project-URL: Homepage, https://github.com/thillsd/piperbook
Provides-Extra: dev
